s4_design_sim_tool/__init__.py
s4_design_sim_tool/_nbdev.py
s4_design_sim_tool/atmosphere.py
s4_design_sim_tool/cli.py
s4_design_sim_tool/core.py
s4_design_sim_tool/foregrounds.py
s4_design_sim_tool/hitmap_wcov.py
s4_design_sim_tool/noise.py
s4_design_sim_tool/ui.py
s4_design_sim_tool-1.1.2.dist-info/LICENSE
s4_design_sim_tool-1.1.2.dist-info/METADATA
s4_design_sim_tool-1.1.2.dist-info/WHEEL
s4_design_sim_tool-1.1.2.dist-info/entry_points.txt
s4_design_sim_tool-1.1.2.dist-info/top_level.txt
s4_design_sim_tool-1.1.2.dist-info/RECORD
