Metadata-Version: 2.1
Name: s4-design-sim-tool
Version: 1.1.2
Summary: CMB-S4 Design Simulation Tool
Home-page: https://github.com/cmb-s4/s4_design_sim_tool/tree/master/
Author: Andrea Zonca
Author-email: code@andreazonca.com
License: Apache Software License 2.0
Keywords: cosmology
Platform: UNKNOWN
Classifier: Development Status :: 3 - Alpha
Classifier: Intended Audience :: Developers
Classifier: License :: OSI Approved :: Apache Software License
Classifier: Natural Language :: English
Classifier: Programming Language :: Python :: 3.6
Classifier: Programming Language :: Python :: 3.7
Classifier: Programming Language :: Python :: 3.8
Requires-Python: >=3.6
Requires-Dist: healpy
Requires-Dist: numpy
Requires-Dist: toml
